otdrparser.py
otdrparser-0.2.1.dist-info/licenses/LICENSE
otdrparser-0.2.1.dist-info/WHEEL
otdrparser-0.2.1.dist-info/METADATA
otdrparser-0.2.1.dist-info/RECORD
