Metadata-Version: 2.4
Name: otdrparser
Version: 0.2.1
Summary: Python library for parsing OTDR files in Telcordia SR-4731 Version 2 format
Author-email: Markus Juenemann <markus@juenemann.net>
License-File: LICENSE
Project-URL: Home, https://github.com/mjuenema/otdrparser
